moltres/__init__.py
moltres/config.py
moltres/py.typed
moltres/dataframe/__init__.py
moltres/dataframe/columns/__init__.py
moltres/dataframe/columns/async_pandas_indexers.py
moltres/dataframe/columns/base_column_wrapper.py
moltres/dataframe/columns/pandas_column.py
moltres/dataframe/columns/pandas_string_accessor.py
moltres/dataframe/columns/polars_column.py
moltres/dataframe/columns/polars_datetime_accessor.py
moltres/dataframe/columns/polars_string_accessor.py
moltres/dataframe/columns/pyspark_column.py
moltres/dataframe/core/__init__.py
moltres/dataframe/core/async_dataframe.py
moltres/dataframe/core/create_dataframe.py
moltres/dataframe/core/dataframe.py
moltres/dataframe/core/interface_common.py
moltres/dataframe/groupby/__init__.py
moltres/dataframe/groupby/async_groupby.py
moltres/dataframe/groupby/async_pandas_groupby.py
moltres/dataframe/groupby/async_polars_groupby.py
moltres/dataframe/groupby/groupby.py
moltres/dataframe/groupby/pandas_groupby.py
moltres/dataframe/groupby/polars_groupby.py
moltres/dataframe/helpers/__init__.py
moltres/dataframe/helpers/dataframe_helpers.py
moltres/dataframe/helpers/file_io_helpers.py
moltres/dataframe/helpers/groupby_helpers.py
moltres/dataframe/helpers/materialization_helpers.py
moltres/dataframe/helpers/pandas_dataframe_helpers.py
moltres/dataframe/helpers/polars_dataframe_helpers.py
moltres/dataframe/helpers/polars_groupby_helpers.py
moltres/dataframe/helpers/reader_helpers.py
moltres/dataframe/helpers/writer_helpers.py
moltres/dataframe/interfaces/__init__.py
moltres/dataframe/interfaces/async_pandas_dataframe.py
moltres/dataframe/interfaces/async_polars_dataframe.py
moltres/dataframe/interfaces/pandas_dataframe.py
moltres/dataframe/interfaces/polars_dataframe.py
moltres/dataframe/io/__init__.py
moltres/dataframe/io/async_reader.py
moltres/dataframe/io/async_writer.py
moltres/dataframe/io/reader.py
moltres/dataframe/io/writer.py
moltres/dataframe/io/readers/__init__.py
moltres/dataframe/io/readers/async_csv_reader.py
moltres-0.23.2.dist-info/METADATA
moltres-0.23.2.dist-info/WHEEL
moltres-0.23.2.dist-info/top_level.txt
moltres-0.23.2.dist-info/RECORD
