Metadata-Version: 2.4
Name: moltres
Version: 0.23.2
Summary: DataFrame API with SQL pushdown execution and real SQL CRUD - the missing layer for SQL in Python
Author-email: Odos Matthews <odosmatthews@gmail.com>
License: MIT License
Project-URL: Homepage, https://github.com/eddiethedean/moltres
Project-URL: Repository, https://github.com/eddiethedean/moltres
Project-URL: Issues, https://github.com/eddiethedean/moltres/issues
Keywords: dataframe,sql,crud,pushdown,etl,data-engineering,sqlalchemy,pandas,polars,spark,database,query-builder
Classifier: Development Status :: 4 - Beta
Classifier: Intended Audience :: Developers
Classifier: Programming Language :: Python
Classifier: Programming Language :: Python :: 3
Classifier: Programming Language :: Python :: 3 :: Only
Classifier: Programming Language :: Python :: 3.9
Classifier: Programming Language :: Python :: 3.10
Classifier: Programming Language :: Python :: 3.11
Classifier: Programming Language :: Python :: 3.12
Classifier: Operating System :: MacOS :: MacOS X
Classifier: Operating System :: Microsoft :: Windows
Classifier: Operating System :: POSIX :: Linux
Classifier: Topic :: Database
Classifier: Topic :: Software Development :: Libraries
Requires-Python: >=3.9
Requires-Dist: SQLAlchemy>=2.0
Requires-Dist: typing-extensions>=4.5
Provides-Extra: polars
Requires-Dist: polars>=1.0; extra == "polars"
Provides-Extra: pandas
Requires-Dist: pandas>=2.1; extra == "pandas"
Provides-Extra: sqlmodel
Requires-Dist: sqlmodel>=0.0.14; extra == "sqlmodel"
Provides-Extra: django
Requires-Dist: django>=3.2; extra == "django"
Provides-Extra: streamlit
Requires-Dist: streamlit>=1.28.0; extra == "streamlit"
Provides-Extra: airflow
Requires-Dist: apache-airflow>=3.0.0; python_version >= "3.10" and extra == "airflow"
Provides-Extra: prefect
Requires-Dist: prefect>=2.0.0; extra == "prefect"
Provides-Extra: dbt
Requires-Dist: dbt-core>=1.5.0; extra == "dbt"
Provides-Extra: async
Requires-Dist: aiofiles>=23.0; extra == "async"
Requires-Dist: greenlet>=3.0.0; extra == "async"
Provides-Extra: async-postgresql
Requires-Dist: aiofiles>=23.0; extra == "async-postgresql"
Requires-Dist: asyncpg>=0.29.0; extra == "async-postgresql"
Requires-Dist: greenlet>=3.0.0; extra == "async-postgresql"
Provides-Extra: async-mysql
Requires-Dist: aiofiles>=23.0; extra == "async-mysql"
Requires-Dist: aiomysql>=0.2.0; extra == "async-mysql"
Requires-Dist: greenlet>=3.0.0; extra == "async-mysql"
Provides-Extra: async-sqlite
Requires-Dist: aiofiles>=23.0; extra == "async-sqlite"
Requires-Dist: aiosqlite>=0.19.0; extra == "async-sqlite"
Requires-Dist: greenlet>=3.0.0; extra == "async-sqlite"
Provides-Extra: dev
Requires-Dist: pytest>=8.0; extra == "dev"
Requires-Dist: pytest-asyncio>=0.21.0; extra == "dev"
Requires-Dist: pytest-cov>=4.1; extra == "dev"
Requires-Dist: pytest-green-light>=0.2.0; extra == "dev"
Requires-Dist: pytest-xdist>=3.5; extra == "dev"
Requires-Dist: mypy>=1.8; extra == "dev"
Requires-Dist: sphinx>=7.0; extra == "dev"
Requires-Dist: sphinx-rtd-theme>=2.0; extra == "dev"
Requires-Dist: ruff>=0.6; extra == "dev"
Requires-Dist: pre-commit>=3.5; extra == "dev"
Requires-Dist: pandas>=2.1; extra == "dev"
Requires-Dist: pandas-stubs>=2.1; extra == "dev"
Requires-Dist: polars>=1.0; extra == "dev"
Requires-Dist: pyarrow>=10.0; extra == "dev"
Requires-Dist: aiofiles>=23.0; extra == "dev"
Requires-Dist: aiosqlite>=0.19.0; extra == "dev"
Requires-Dist: asyncpg>=0.29.0; extra == "dev"
Requires-Dist: greenlet>=3.0.0; extra == "dev"
Requires-Dist: testing.postgresql>=1.3.0; extra == "dev"
Requires-Dist: testing.mysqld>=1.4.0; extra == "dev"
Requires-Dist: psycopg2-binary>=2.9.0; extra == "dev"
Requires-Dist: pymysql>=1.0.0; extra == "dev"
Requires-Dist: duckdb-engine>=0.9.0; extra == "dev"
Requires-Dist: sqlmodel>=0.0.14; extra == "dev"
Requires-Dist: fastapi>=0.100.0; extra == "dev"
Requires-Dist: uvicorn>=0.23.0; extra == "dev"
Requires-Dist: django>=3.2; extra == "dev"
Requires-Dist: streamlit>=1.28.0; extra == "dev"
Requires-Dist: apache-airflow>=3.0.0; python_version >= "3.10" and extra == "dev"
Requires-Dist: prefect>=2.0.0; extra == "dev"
Requires-Dist: dbt-core>=1.5.0; extra == "dev"
